{"cameraMode":{"drawMode":0,"name":"Shaded","section":"Shading Mode"},"sceneLighting":true,"audioPlay":false,"sceneViewState":{"showFog":true,"showMaterialUpdate":false,"showSkybox":true,"showFlares":true,"showImageEffects":true,"showParticleSystems":true,"showVisualEffectGraphs":true,"m_FxEnabled":true},"in2DMode":false,"pivot":{"x":-30.16803741455078,"y":-6.417430877685547,"z":46.53620529174805},"rotation":{"x":0.30090272426605227,"y":0.11124316602945328,"z":-0.035364627838134769,"w":0.9464922547340393},"size":377.8141174316406,"orthographic":false}